{
  "url": "https://api.github.com/repos/ethereum/go-ethereum/issues/15695",
  "repository_url": "https://api.github.com/repos/ethereum/go-ethereum",
  "labels_url": "https://api.github.com/repos/ethereum/go-ethereum/issues/15695/labels{/name}",
  "comments_url": "https://api.github.com/repos/ethereum/go-ethereum/issues/15695/comments",
  "events_url": "https://api.github.com/repos/ethereum/go-ethereum/issues/15695/events",
  "html_url": "https://github.com/ethereum/go-ethereum/issues/15695",
  "id": 282743530,
  "node_id": "MDU6SXNzdWUyODI3NDM1MzA=",
  "number": 15695,
  "title": "How long do I need to sit here starring at \"Looking for peers...\" in light mode? ",
  "user": {
    "login": "KainniaK",
    "id": 34470588,
    "node_id": "MDQ6VXNlcjM0NDcwNTg4",
    "avatar_url": "https://avatars.githubusercontent.com/u/34470588?v=4",
    "gravatar_id": "",
    "url": "https://api.github.com/users/KainniaK",
    "html_url": "https://github.com/KainniaK",
    "followers_url": "https://api.github.com/users/KainniaK/followers",
    "following_url": "https://api.github.com/users/KainniaK/following{/other_user}",
    "gists_url": "https://api.github.com/users/KainniaK/gists{/gist_id}",
    "starred_url": "https://api.github.com/users/KainniaK/starred{/owner}{/repo}",
    "subscriptions_url": "https://api.github.com/users/KainniaK/subscriptions",
    "organizations_url": "https://api.github.com/users/KainniaK/orgs",
    "repos_url": "https://api.github.com/users/KainniaK/repos",
    "events_url": "https://api.github.com/users/KainniaK/events{/privacy}",
    "received_events_url": "https://api.github.com/users/KainniaK/received_events",
    "type": "User",
    "site_admin": false
  },
  "labels": [
    {
      "id": 856638432,
      "node_id": "MDU6TGFiZWw4NTY2Mzg0MzI=",
      "url": "https://api.github.com/repos/ethereum/go-ethereum/labels/status:inactive",
      "name": "status:inactive",
      "color": "ffffff",
      "default": false,
      "description": null
    }
  ],
  "state": "closed",
  "locked": false,
  "assignee": null,
  "assignees": [

  ],
  "milestone": null,
  "comments": 4,
  "created_at": "2017-12-18T01:41:36Z",
  "updated_at": "2019-02-04T11:44:08Z",
  "closed_at": "2019-02-04T11:44:08Z",
  "author_association": "NONE",
  "active_lock_reason": null,
  "body": "Seriously, I would like to make a payment. I am very sorry I don't have a big enough hard drive to run Ethereum Wallet in full or fast mode. I am sorry, I wish it was different. I wish my internet was  faster. I wish a lot of things. But right now I would like to make a payment using Ethereum, I don't want to be sorry about that.  Opening up Ethereum Wallet is a gamble right now, if I do it at the correct time during the day I might connect with one peer long enough to actually make a transaction.\r\n\r\nCome one, please fix this!!!!! I need Ethereum Wallet to be reliable enough!!!! ",
  "closed_by": {
    "login": "stale[bot]",
    "id": 26384082,
    "node_id": "MDM6Qm90MjYzODQwODI=",
    "avatar_url": "https://avatars.githubusercontent.com/in/1724?v=4",
    "gravatar_id": "",
    "url": "https://api.github.com/users/stale%5Bbot%5D",
    "html_url": "https://github.com/apps/stale",
    "followers_url": "https://api.github.com/users/stale%5Bbot%5D/followers",
    "following_url": "https://api.github.com/users/stale%5Bbot%5D/following{/other_user}",
    "gists_url": "https://api.github.com/users/stale%5Bbot%5D/gists{/gist_id}",
    "starred_url": "https://api.github.com/users/stale%5Bbot%5D/starred{/owner}{/repo}",
    "subscriptions_url": "https://api.github.com/users/stale%5Bbot%5D/subscriptions",
    "organizations_url": "https://api.github.com/users/stale%5Bbot%5D/orgs",
    "repos_url": "https://api.github.com/users/stale%5Bbot%5D/repos",
    "events_url": "https://api.github.com/users/stale%5Bbot%5D/events{/privacy}",
    "received_events_url": "https://api.github.com/users/stale%5Bbot%5D/received_events",
    "type": "Bot",
    "site_admin": false
  },
  "reactions": {
    "url": "https://api.github.com/repos/ethereum/go-ethereum/issues/15695/reactions",
    "total_count": 2,
    "+1": 1,
    "-1": 1,
    "laugh": 0,
    "hooray": 0,
    "confused": 0,
    "heart": 0,
    "rocket": 0,
    "eyes": 0
  },
  "timeline_url": "https://api.github.com/repos/ethereum/go-ethereum/issues/15695/timeline",
  "performed_via_github_app": null,
  "state_reason": "completed"
}
[
  {
    "url": "https://api.github.com/repos/ethereum/go-ethereum/issues/comments/352306572",
    "html_url": "https://github.com/ethereum/go-ethereum/issues/15695#issuecomment-352306572",
    "issue_url": "https://api.github.com/repos/ethereum/go-ethereum/issues/15695",
    "id": 352306572,
    "node_id": "MDEyOklzc3VlQ29tbWVudDM1MjMwNjU3Mg==",
    "user": {
      "login": "lmars",
      "id": 488515,
      "node_id": "MDQ6VXNlcjQ4ODUxNQ==",
      "avatar_url": "https://avatars.githubusercontent.com/u/488515?v=4",
      "gravatar_id": "",
      "url": "https://api.github.com/users/lmars",
      "html_url": "https://github.com/lmars",
      "followers_url": "https://api.github.com/users/lmars/followers",
      "following_url": "https://api.github.com/users/lmars/following{/other_user}",
      "gists_url": "https://api.github.com/users/lmars/gists{/gist_id}",
      "starred_url": "https://api.github.com/users/lmars/starred{/owner}{/repo}",
      "subscriptions_url": "https://api.github.com/users/lmars/subscriptions",
      "organizations_url": "https://api.github.com/users/lmars/orgs",
      "repos_url": "https://api.github.com/users/lmars/repos",
      "events_url": "https://api.github.com/users/lmars/events{/privacy}",
      "received_events_url": "https://api.github.com/users/lmars/received_events",
      "type": "User",
      "site_admin": false
    },
    "created_at": "2017-12-18T01:55:13Z",
    "updated_at": "2017-12-18T01:55:13Z",
    "author_association": "CONTRIBUTOR",
    "body": "@KainniaK have you considered using [MetaMask](https://metamask.io/) or [MyEtherWallet](https://www.myetherwallet.com/), both of which store your keys locally but support connecting to public Ethereum gateways like [Infura](https://infura.io/) to send signed transactions?\r\n\r\nAlso, I think we should keep issues on GitHub for bugs in the go-ethereum code, whereas what you are reporting is more a community issue (see my comment [here](https://github.com/ethereum/go-ethereum/issues/15454#issuecomment-352216741)).",
    "reactions": {
      "url": "https://api.github.com/repos/ethereum/go-ethereum/issues/comments/352306572/reactions",
      "total_count": 2,
      "+1": 0,
      "-1": 1,
      "laugh": 0,
      "hooray": 1,
      "confused": 0,
      "heart": 0,
      "rocket": 0,
      "eyes": 0
    },
    "performed_via_github_app": null
  },
  {
    "url": "https://api.github.com/repos/ethereum/go-ethereum/issues/comments/352307343",
    "html_url": "https://github.com/ethereum/go-ethereum/issues/15695#issuecomment-352307343",
    "issue_url": "https://api.github.com/repos/ethereum/go-ethereum/issues/15695",
    "id": 352307343,
    "node_id": "MDEyOklzc3VlQ29tbWVudDM1MjMwNzM0Mw==",
    "user": {
      "login": "KainniaK",
      "id": 34470588,
      "node_id": "MDQ6VXNlcjM0NDcwNTg4",
      "avatar_url": "https://avatars.githubusercontent.com/u/34470588?v=4",
      "gravatar_id": "",
      "url": "https://api.github.com/users/KainniaK",
      "html_url": "https://github.com/KainniaK",
      "followers_url": "https://api.github.com/users/KainniaK/followers",
      "following_url": "https://api.github.com/users/KainniaK/following{/other_user}",
      "gists_url": "https://api.github.com/users/KainniaK/gists{/gist_id}",
      "starred_url": "https://api.github.com/users/KainniaK/starred{/owner}{/repo}",
      "subscriptions_url": "https://api.github.com/users/KainniaK/subscriptions",
      "organizations_url": "https://api.github.com/users/KainniaK/orgs",
      "repos_url": "https://api.github.com/users/KainniaK/repos",
      "events_url": "https://api.github.com/users/KainniaK/events{/privacy}",
      "received_events_url": "https://api.github.com/users/KainniaK/received_events",
      "type": "User",
      "site_admin": false
    },
    "created_at": "2017-12-18T02:02:31Z",
    "updated_at": "2017-12-18T02:02:31Z",
    "author_association": "NONE",
    "body": "Will these allow me so see my accounts even when I am offline? Also how safe is it to have my brower mixed with Ethereum? I don't trust browsers to much. ",
    "reactions": {
      "url": "https://api.github.com/repos/ethereum/go-ethereum/issues/comments/352307343/reactions",
      "total_count": 2,
      "+1": 1,
      "-1": 1,
      "laugh": 0,
      "hooray": 0,
      "confused": 0,
      "heart": 0,
      "rocket": 0,
      "eyes": 0
    },
    "performed_via_github_app": null
  },
  {
    "url": "https://api.github.com/repos/ethereum/go-ethereum/issues/comments/352447960",
    "html_url": "https://github.com/ethereum/go-ethereum/issues/15695#issuecomment-352447960",
    "issue_url": "https://api.github.com/repos/ethereum/go-ethereum/issues/15695",
    "id": 352447960,
    "node_id": "MDEyOklzc3VlQ29tbWVudDM1MjQ0Nzk2MA==",
    "user": {
      "login": "ligi",
      "id": 111600,
      "node_id": "MDQ6VXNlcjExMTYwMA==",
      "avatar_url": "https://avatars.githubusercontent.com/u/111600?v=4",
      "gravatar_id": "",
      "url": "https://api.github.com/users/ligi",
      "html_url": "https://github.com/ligi",
      "followers_url": "https://api.github.com/users/ligi/followers",
      "following_url": "https://api.github.com/users/ligi/following{/other_user}",
      "gists_url": "https://api.github.com/users/ligi/gists{/gist_id}",
      "starred_url": "https://api.github.com/users/ligi/starred{/owner}{/repo}",
      "subscriptions_url": "https://api.github.com/users/ligi/subscriptions",
      "organizations_url": "https://api.github.com/users/ligi/orgs",
      "repos_url": "https://api.github.com/users/ligi/repos",
      "events_url": "https://api.github.com/users/ligi/events{/privacy}",
      "received_events_url": "https://api.github.com/users/ligi/received_events",
      "type": "User",
      "site_admin": false
    },
    "created_at": "2017-12-18T14:55:01Z",
    "updated_at": "2017-12-18T14:55:01Z",
    "author_association": "MEMBER",
    "body": " > Will these allow me so see my accounts even when I am offline? Also how safe is it to have my brower mixed with Ethereum? I don't trust browsers to much.\r\n\r\nmaybe WALLETH is an option for you - http://walleth.org\r\n\r\nyou can see your accounts when you are offline and no need to trust browsers (I understand your feeling there). It also does not need that good of an internet-connection as a full-node needs.",
    "reactions": {
      "url": "https://api.github.com/repos/ethereum/go-ethereum/issues/comments/352447960/reactions",
      "total_count": 0,
      "+1": 0,
      "-1": 0,
      "laugh": 0,
      "hooray": 0,
      "confused": 0,
      "heart": 0,
      "rocket": 0,
      "eyes": 0
    },
    "performed_via_github_app": null
  },
  {
    "url": "https://api.github.com/repos/ethereum/go-ethereum/issues/comments/448761388",
    "html_url": "https://github.com/ethereum/go-ethereum/issues/15695#issuecomment-448761388",
    "issue_url": "https://api.github.com/repos/ethereum/go-ethereum/issues/15695",
    "id": 448761388,
    "node_id": "MDEyOklzc3VlQ29tbWVudDQ0ODc2MTM4OA==",
    "user": {
      "login": "stale[bot]",
      "id": 26384082,
      "node_id": "MDM6Qm90MjYzODQwODI=",
      "avatar_url": "https://avatars.githubusercontent.com/in/1724?v=4",
      "gravatar_id": "",
      "url": "https://api.github.com/users/stale%5Bbot%5D",
      "html_url": "https://github.com/apps/stale",
      "followers_url": "https://api.github.com/users/stale%5Bbot%5D/followers",
      "following_url": "https://api.github.com/users/stale%5Bbot%5D/following{/other_user}",
      "gists_url": "https://api.github.com/users/stale%5Bbot%5D/gists{/gist_id}",
      "starred_url": "https://api.github.com/users/stale%5Bbot%5D/starred{/owner}{/repo}",
      "subscriptions_url": "https://api.github.com/users/stale%5Bbot%5D/subscriptions",
      "organizations_url": "https://api.github.com/users/stale%5Bbot%5D/orgs",
      "repos_url": "https://api.github.com/users/stale%5Bbot%5D/repos",
      "events_url": "https://api.github.com/users/stale%5Bbot%5D/events{/privacy}",
      "received_events_url": "https://api.github.com/users/stale%5Bbot%5D/received_events",
      "type": "Bot",
      "site_admin": false
    },
    "created_at": "2018-12-19T22:08:18Z",
    "updated_at": "2018-12-19T22:08:18Z",
    "author_association": "NONE",
    "body": "This issue has been automatically marked as stale because it has not had recent activity. It will be closed if no further activity occurs. Thank you for your contributions.\n",
    "reactions": {
      "url": "https://api.github.com/repos/ethereum/go-ethereum/issues/comments/448761388/reactions",
      "total_count": 0,
      "+1": 0,
      "-1": 0,
      "laugh": 0,
      "hooray": 0,
      "confused": 0,
      "heart": 0,
      "rocket": 0,
      "eyes": 0
    },
    "performed_via_github_app": null
  }
]
