{
  "url": "https://api.github.com/repos/ethereum/go-ethereum/issues/21905",
  "repository_url": "https://api.github.com/repos/ethereum/go-ethereum",
  "labels_url": "https://api.github.com/repos/ethereum/go-ethereum/issues/21905/labels{/name}",
  "comments_url": "https://api.github.com/repos/ethereum/go-ethereum/issues/21905/comments",
  "events_url": "https://api.github.com/repos/ethereum/go-ethereum/issues/21905/events",
  "html_url": "https://github.com/ethereum/go-ethereum/issues/21905",
  "id": 751222230,
  "node_id": "MDU6SXNzdWU3NTEyMjIyMzA=",
  "number": 21905,
  "title": "How can I mint my own(raw) token on my own public chain and contract tokens which is deploy on it at the same time?",
  "user": {
    "login": "Jackie-Zhong",
    "id": 39180014,
    "node_id": "MDQ6VXNlcjM5MTgwMDE0",
    "avatar_url": "https://avatars.githubusercontent.com/u/39180014?v=4",
    "gravatar_id": "",
    "url": "https://api.github.com/users/Jackie-Zhong",
    "html_url": "https://github.com/Jackie-Zhong",
    "followers_url": "https://api.github.com/users/Jackie-Zhong/followers",
    "following_url": "https://api.github.com/users/Jackie-Zhong/following{/other_user}",
    "gists_url": "https://api.github.com/users/Jackie-Zhong/gists{/gist_id}",
    "starred_url": "https://api.github.com/users/Jackie-Zhong/starred{/owner}{/repo}",
    "subscriptions_url": "https://api.github.com/users/Jackie-Zhong/subscriptions",
    "organizations_url": "https://api.github.com/users/Jackie-Zhong/orgs",
    "repos_url": "https://api.github.com/users/Jackie-Zhong/repos",
    "events_url": "https://api.github.com/users/Jackie-Zhong/events{/privacy}",
    "received_events_url": "https://api.github.com/users/Jackie-Zhong/received_events",
    "type": "User",
    "site_admin": false
  },
  "labels": [
    {
      "id": 268304226,
      "node_id": "MDU6TGFiZWwyNjgzMDQyMjY=",
      "url": "https://api.github.com/repos/ethereum/go-ethereum/labels/type:docs",
      "name": "type:docs",
      "color": "fef2c0",
      "default": false,
      "description": null
    }
  ],
  "state": "closed",
  "locked": false,
  "assignee": null,
  "assignees": [

  ],
  "milestone": null,
  "comments": 1,
  "created_at": "2020-11-26T01:56:08Z",
  "updated_at": "2020-11-26T02:07:09Z",
  "closed_at": "2020-11-26T02:07:08Z",
  "author_association": "NONE",
  "active_lock_reason": null,
  "body": "hi,good to everybody!\r\n   I have my own public chain of proof of work algorithm. \r\n   I deploy an erc20 contract token to this public chain,which it named dyc token.\r\n\r\nmy problem is:\r\n   I use the mill to mint token on my own public chain,and i want to mint the dyc token at the sametime. Is this feasible? If it can,how to do?\r\n\r\n你好，各位！\r\n   我有一条pow算法的公链\r\n   我部署了一份erc20合约代币叫做dyc在我的公链上。\r\n\r\n我的问题是：\r\n   我使用矿机在我这条公链上挖代币，而且我又能同时挖dyc token，这可行吗？如果可以的话，应该怎么做？",
  "closed_by": {
    "login": "ligi",
    "id": 111600,
    "node_id": "MDQ6VXNlcjExMTYwMA==",
    "avatar_url": "https://avatars.githubusercontent.com/u/111600?v=4",
    "gravatar_id": "",
    "url": "https://api.github.com/users/ligi",
    "html_url": "https://github.com/ligi",
    "followers_url": "https://api.github.com/users/ligi/followers",
    "following_url": "https://api.github.com/users/ligi/following{/other_user}",
    "gists_url": "https://api.github.com/users/ligi/gists{/gist_id}",
    "starred_url": "https://api.github.com/users/ligi/starred{/owner}{/repo}",
    "subscriptions_url": "https://api.github.com/users/ligi/subscriptions",
    "organizations_url": "https://api.github.com/users/ligi/orgs",
    "repos_url": "https://api.github.com/users/ligi/repos",
    "events_url": "https://api.github.com/users/ligi/events{/privacy}",
    "received_events_url": "https://api.github.com/users/ligi/received_events",
    "type": "User",
    "site_admin": false
  },
  "reactions": {
    "url": "https://api.github.com/repos/ethereum/go-ethereum/issues/21905/reactions",
    "total_count": 0,
    "+1": 0,
    "-1": 0,
    "laugh": 0,
    "hooray": 0,
    "confused": 0,
    "heart": 0,
    "rocket": 0,
    "eyes": 0
  },
  "timeline_url": "https://api.github.com/repos/ethereum/go-ethereum/issues/21905/timeline",
  "performed_via_github_app": null,
  "state_reason": "completed"
}
[
  {
    "url": "https://api.github.com/repos/ethereum/go-ethereum/issues/comments/734031002",
    "html_url": "https://github.com/ethereum/go-ethereum/issues/21905#issuecomment-734031002",
    "issue_url": "https://api.github.com/repos/ethereum/go-ethereum/issues/21905",
    "id": 734031002,
    "node_id": "MDEyOklzc3VlQ29tbWVudDczNDAzMTAwMg==",
    "user": {
      "login": "ligi",
      "id": 111600,
      "node_id": "MDQ6VXNlcjExMTYwMA==",
      "avatar_url": "https://avatars.githubusercontent.com/u/111600?v=4",
      "gravatar_id": "",
      "url": "https://api.github.com/users/ligi",
      "html_url": "https://github.com/ligi",
      "followers_url": "https://api.github.com/users/ligi/followers",
      "following_url": "https://api.github.com/users/ligi/following{/other_user}",
      "gists_url": "https://api.github.com/users/ligi/gists{/gist_id}",
      "starred_url": "https://api.github.com/users/ligi/starred{/owner}{/repo}",
      "subscriptions_url": "https://api.github.com/users/ligi/subscriptions",
      "organizations_url": "https://api.github.com/users/ligi/orgs",
      "repos_url": "https://api.github.com/users/ligi/repos",
      "events_url": "https://api.github.com/users/ligi/events{/privacy}",
      "received_events_url": "https://api.github.com/users/ligi/received_events",
      "type": "User",
      "site_admin": false
    },
    "created_at": "2020-11-26T02:07:08Z",
    "updated_at": "2020-11-26T02:07:08Z",
    "author_association": "MEMBER",
    "body": "Please help to keep this issue-tracker clean and only for real issues with go-ethereum. For questions please go to http://ethereum.stackexchange.com\r\n\r\nIf the issue-tracker gets littered with questions - it is really hard to keep track of real issues. So I am sorry to close this issue - but feel free to answer here with the link to your question on stackexchange. Thanks!",
    "reactions": {
      "url": "https://api.github.com/repos/ethereum/go-ethereum/issues/comments/734031002/reactions",
      "total_count": 0,
      "+1": 0,
      "-1": 0,
      "laugh": 0,
      "hooray": 0,
      "confused": 0,
      "heart": 0,
      "rocket": 0,
      "eyes": 0
    },
    "performed_via_github_app": null
  }
]
