{
  "url": "https://api.github.com/repos/ethereum/solidity/issues/974",
  "repository_url": "https://api.github.com/repos/ethereum/solidity",
  "labels_url": "https://api.github.com/repos/ethereum/solidity/issues/974/labels{/name}",
  "comments_url": "https://api.github.com/repos/ethereum/solidity/issues/974/comments",
  "events_url": "https://api.github.com/repos/ethereum/solidity/issues/974/events",
  "html_url": "https://github.com/ethereum/solidity/issues/974",
  "id": 173940544,
  "node_id": "MDU6SXNzdWUxNzM5NDA1NDQ=",
  "number": 974,
  "title": "When an array is in a struct it should be possible to specify the number of bytes used to store the length",
  "user": {
    "login": "ethernomad",
    "id": 161566,
    "node_id": "MDQ6VXNlcjE2MTU2Ng==",
    "avatar_url": "https://avatars.githubusercontent.com/u/161566?v=4",
    "gravatar_id": "",
    "url": "https://api.github.com/users/ethernomad",
    "html_url": "https://github.com/ethernomad",
    "followers_url": "https://api.github.com/users/ethernomad/followers",
    "following_url": "https://api.github.com/users/ethernomad/following{/other_user}",
    "gists_url": "https://api.github.com/users/ethernomad/gists{/gist_id}",
    "starred_url": "https://api.github.com/users/ethernomad/starred{/owner}{/repo}",
    "subscriptions_url": "https://api.github.com/users/ethernomad/subscriptions",
    "organizations_url": "https://api.github.com/users/ethernomad/orgs",
    "repos_url": "https://api.github.com/users/ethernomad/repos",
    "events_url": "https://api.github.com/users/ethernomad/events{/privacy}",
    "received_events_url": "https://api.github.com/users/ethernomad/received_events",
    "type": "User",
    "site_admin": false
  },
  "labels": [

  ],
  "state": "closed",
  "locked": false,
  "assignee": null,
  "assignees": [

  ],
  "milestone": null,
  "comments": 3,
  "created_at": "2016-08-30T06:35:58Z",
  "updated_at": "2017-03-08T10:23:06Z",
  "closed_at": "2017-03-08T10:23:06Z",
  "author_association": "CONTRIBUTOR",
  "active_lock_reason": null,
  "body": "Array lengths are always stored as a single slot. Often 1 to 3 bytes would be sufficient. It would be great if the maximum length could be specified and the length state be packed into a struct.\n\nCurrently this requires a lot of custom coding.\n",
  "closed_by": {
    "login": "chriseth",
    "id": 9073706,
    "node_id": "MDQ6VXNlcjkwNzM3MDY=",
    "avatar_url": "https://avatars.githubusercontent.com/u/9073706?v=4",
    "gravatar_id": "",
    "url": "https://api.github.com/users/chriseth",
    "html_url": "https://github.com/chriseth",
    "followers_url": "https://api.github.com/users/chriseth/followers",
    "following_url": "https://api.github.com/users/chriseth/following{/other_user}",
    "gists_url": "https://api.github.com/users/chriseth/gists{/gist_id}",
    "starred_url": "https://api.github.com/users/chriseth/starred{/owner}{/repo}",
    "subscriptions_url": "https://api.github.com/users/chriseth/subscriptions",
    "organizations_url": "https://api.github.com/users/chriseth/orgs",
    "repos_url": "https://api.github.com/users/chriseth/repos",
    "events_url": "https://api.github.com/users/chriseth/events{/privacy}",
    "received_events_url": "https://api.github.com/users/chriseth/received_events",
    "type": "User",
    "site_admin": false
  },
  "reactions": {
    "url": "https://api.github.com/repos/ethereum/solidity/issues/974/reactions",
    "total_count": 0,
    "+1": 0,
    "-1": 0,
    "laugh": 0,
    "hooray": 0,
    "confused": 0,
    "heart": 0,
    "rocket": 0,
    "eyes": 0
  },
  "timeline_url": "https://api.github.com/repos/ethereum/solidity/issues/974/timeline",
  "performed_via_github_app": null,
  "state_reason": "completed"
}
[
  {
    "url": "https://api.github.com/repos/ethereum/solidity/issues/comments/243472134",
    "html_url": "https://github.com/ethereum/solidity/issues/974#issuecomment-243472134",
    "issue_url": "https://api.github.com/repos/ethereum/solidity/issues/974",
    "id": 243472134,
    "node_id": "MDEyOklzc3VlQ29tbWVudDI0MzQ3MjEzNA==",
    "user": {
      "login": "chriseth",
      "id": 9073706,
      "node_id": "MDQ6VXNlcjkwNzM3MDY=",
      "avatar_url": "https://avatars.githubusercontent.com/u/9073706?v=4",
      "gravatar_id": "",
      "url": "https://api.github.com/users/chriseth",
      "html_url": "https://github.com/chriseth",
      "followers_url": "https://api.github.com/users/chriseth/followers",
      "following_url": "https://api.github.com/users/chriseth/following{/other_user}",
      "gists_url": "https://api.github.com/users/chriseth/gists{/gist_id}",
      "starred_url": "https://api.github.com/users/chriseth/starred{/owner}{/repo}",
      "subscriptions_url": "https://api.github.com/users/chriseth/subscriptions",
      "organizations_url": "https://api.github.com/users/chriseth/orgs",
      "repos_url": "https://api.github.com/users/chriseth/repos",
      "events_url": "https://api.github.com/users/chriseth/events{/privacy}",
      "received_events_url": "https://api.github.com/users/chriseth/received_events",
      "type": "User",
      "site_admin": false
    },
    "created_at": "2016-08-30T15:08:54Z",
    "updated_at": "2016-08-30T15:08:54Z",
    "author_association": "MEMBER",
    "body": "What is the goal you want to achieve here? The array length deliberately occupies a full slot so that offsets of the data area (= sha3 of the length slot) are unique.\n",
    "reactions": {
      "url": "https://api.github.com/repos/ethereum/solidity/issues/comments/243472134/reactions",
      "total_count": 0,
      "+1": 0,
      "-1": 0,
      "laugh": 0,
      "hooray": 0,
      "confused": 0,
      "heart": 0,
      "rocket": 0,
      "eyes": 0
    },
    "performed_via_github_app": null
  },
  {
    "url": "https://api.github.com/repos/ethereum/solidity/issues/comments/243578259",
    "html_url": "https://github.com/ethereum/solidity/issues/974#issuecomment-243578259",
    "issue_url": "https://api.github.com/repos/ethereum/solidity/issues/974",
    "id": 243578259,
    "node_id": "MDEyOklzc3VlQ29tbWVudDI0MzU3ODI1OQ==",
    "user": {
      "login": "ethernomad",
      "id": 161566,
      "node_id": "MDQ6VXNlcjE2MTU2Ng==",
      "avatar_url": "https://avatars.githubusercontent.com/u/161566?v=4",
      "gravatar_id": "",
      "url": "https://api.github.com/users/ethernomad",
      "html_url": "https://github.com/ethernomad",
      "followers_url": "https://api.github.com/users/ethernomad/followers",
      "following_url": "https://api.github.com/users/ethernomad/following{/other_user}",
      "gists_url": "https://api.github.com/users/ethernomad/gists{/gist_id}",
      "starred_url": "https://api.github.com/users/ethernomad/starred{/owner}{/repo}",
      "subscriptions_url": "https://api.github.com/users/ethernomad/subscriptions",
      "organizations_url": "https://api.github.com/users/ethernomad/orgs",
      "repos_url": "https://api.github.com/users/ethernomad/repos",
      "events_url": "https://api.github.com/users/ethernomad/events{/privacy}",
      "received_events_url": "https://api.github.com/users/ethernomad/received_events",
      "type": "User",
      "site_admin": false
    },
    "created_at": "2016-08-30T20:57:02Z",
    "updated_at": "2016-08-30T20:57:02Z",
    "author_association": "CONTRIBUTOR",
    "body": "In [this contract](https://github.com/bluedroplet/blobstore-ethereum/blob/master/blobstore.sol) I packed the length of the packedRevisionBlockNumbers mapping (numRevisions) into the struct. If I used the built-in array functionality the struct would be 2 slots instead of 1.\n",
    "reactions": {
      "url": "https://api.github.com/repos/ethereum/solidity/issues/comments/243578259/reactions",
      "total_count": 0,
      "+1": 0,
      "-1": 0,
      "laugh": 0,
      "hooray": 0,
      "confused": 0,
      "heart": 0,
      "rocket": 0,
      "eyes": 0
    },
    "performed_via_github_app": null
  },
  {
    "url": "https://api.github.com/repos/ethereum/solidity/issues/comments/285003642",
    "html_url": "https://github.com/ethereum/solidity/issues/974#issuecomment-285003642",
    "issue_url": "https://api.github.com/repos/ethereum/solidity/issues/974",
    "id": 285003642,
    "node_id": "MDEyOklzc3VlQ29tbWVudDI4NTAwMzY0Mg==",
    "user": {
      "login": "chriseth",
      "id": 9073706,
      "node_id": "MDQ6VXNlcjkwNzM3MDY=",
      "avatar_url": "https://avatars.githubusercontent.com/u/9073706?v=4",
      "gravatar_id": "",
      "url": "https://api.github.com/users/chriseth",
      "html_url": "https://github.com/chriseth",
      "followers_url": "https://api.github.com/users/chriseth/followers",
      "following_url": "https://api.github.com/users/chriseth/following{/other_user}",
      "gists_url": "https://api.github.com/users/chriseth/gists{/gist_id}",
      "starred_url": "https://api.github.com/users/chriseth/starred{/owner}{/repo}",
      "subscriptions_url": "https://api.github.com/users/chriseth/subscriptions",
      "organizations_url": "https://api.github.com/users/chriseth/orgs",
      "repos_url": "https://api.github.com/users/chriseth/repos",
      "events_url": "https://api.github.com/users/chriseth/events{/privacy}",
      "received_events_url": "https://api.github.com/users/chriseth/received_events",
      "type": "User",
      "site_admin": false
    },
    "created_at": "2017-03-08T10:23:06Z",
    "updated_at": "2017-03-08T10:23:06Z",
    "author_association": "MEMBER",
    "body": "This adds a complication that is only beneficial in very specific cases. Closing.",
    "reactions": {
      "url": "https://api.github.com/repos/ethereum/solidity/issues/comments/285003642/reactions",
      "total_count": 0,
      "+1": 0,
      "-1": 0,
      "laugh": 0,
      "hooray": 0,
      "confused": 0,
      "heart": 0,
      "rocket": 0,
      "eyes": 0
    },
    "performed_via_github_app": null
  }
]
